cached_iterators/__init__.py
cached_iterators/_async.py
cached_iterators/sync.py
cached_iterators-1.0.3.dist-info/METADATA
cached_iterators-1.0.3.dist-info/WHEEL
cached_iterators-1.0.3.dist-info/RECORD
