Metadata-Version: 2.1
Name: cached-iterators
Version: 1.0.3
Summary: A Python library providing cacheable iterator wrappers for both synchronous and asynchronous iterators.
Home-page: https://github.com/ulbwa/cached-iterators
Author: ульба
Author-email: ulbwa@icloud.com
Requires-Python: >=3.10,<4.0
Classifier: Programming Language :: Python :: 3
Classifier: Programming Language :: Python :: 3.10
Classifier: Programming Language :: Python :: 3.11
Classifier: Programming Language :: Python :: 3.12
Project-URL: Repository, https://github.com/ulbwa/cached-iterators
